panasonic_programmable_keys/__init__.py
panasonic_programmable_keys/__main__.py
panasonic_programmable_keys/__version__.py
panasonic_programmable_keys/cli/__init__.py
panasonic_programmable_keys/cli/base.py
panasonic_programmable_keys/cli/cli.py
panasonic_programmable_keys/gui/__init__.py
panasonic_programmable_keys/gui/gui.py
panasonic_programmable_keys/input/__init__.py
panasonic_programmable_keys/input/capture.py
panasonic_programmable_keys/input/handle.py
panasonic_programmable_keys/input/models.py
panasonic_programmable_keys/install/__init__.py
panasonic_programmable_keys/install/install.py
panasonic_programmable_keys/install/templates/panasonic-programmable-keys-client.service.j2
panasonic_programmable_keys/install/templates/panasonic-programmable-keys-server.service.j2
panasonic_programmable_keys/install/templates/panasonic-programmable-keys.application.j2
panasonic_programmable_keys/rpc/__init__.py
panasonic_programmable_keys/rpc/client.py
panasonic_programmable_keys/rpc/server.py
panasonic_programmable_keys/util/__init__.py
panasonic_programmable_keys/util/config.py
panasonic_programmable_keys/util/defaults.toml
panasonic_programmable_keys/util/helpers.py
panasonic_programmable_keys/util/logging.py
panasonic_programmable_keys/util/shell.py
panasonic_programmable_keys-0.2.4.dist-info/LICENSE
panasonic_programmable_keys-0.2.4.dist-info/METADATA
panasonic_programmable_keys-0.2.4.dist-info/WHEEL
panasonic_programmable_keys-0.2.4.dist-info/entry_points.txt
panasonic_programmable_keys-0.2.4.dist-info/top_level.txt
panasonic_programmable_keys-0.2.4.dist-info/RECORD
