Metadata-Version: 2.1
Name: panasonic-programmable-keys
Version: 0.2.4
Summary: A GUI applicaiton to define the programmable keys for Panasonic Toughbook keyboards
Author-email: James Harmison <jharmison@redhat.com>
License: Copyright 2024 James Harmison <jharmison@redhat.com>
Project-URL: Source, https://github.com/jharmison-redhat/panasonic-programmable-keys
Project-URL: Documentation, https://github.com/jharmison-redhat/panasonic-programmable-keys
Classifier: License :: OSI Approved :: BSD License
Classifier: Operating System :: POSIX :: Linux
Requires-Python: >=3.11
License-File: LICENSE
Requires-Dist: dynaconf<3.3.0,>=3.2.6
Requires-Dist: pydantic<2.10.0,>=2.9.2
Requires-Dist: typer<0.13,>=0.12.5
Requires-Dist: PyQt5<5.16,>=5.15.11
Requires-Dist: Pyro5<6.0,>=5.15
Requires-Dist: Jinja2<3.2.0,>=3.1.4
Requires-Dist: watchdog<6.1.0,>=6.0.0
Provides-Extra: dev
Requires-Dist: tox; extra == "dev"
Requires-Dist: PyQt5-stubs; extra == "dev"
Requires-Dist: pytest; extra == "dev"
